telegram/__init__.py
telegram/__main__.py
telegram/_birthdate.py
telegram/_bot.py
telegram/_botcommand.py
telegram/_botcommandscope.py
telegram/_botdescription.py
telegram/_botname.py
telegram/_business.py
telegram/_callbackquery.py
telegram/_chat.py
telegram/_chatadministratorrights.py
telegram/_chatbackground.py
telegram/_chatboost.py
telegram/_chatfullinfo.py
telegram/_chatinvitelink.py
telegram/_chatjoinrequest.py
telegram/_chatlocation.py
telegram/_chatmember.py
telegram/_chatmemberupdated.py
telegram/_chatpermissions.py
telegram/_choseninlineresult.py
telegram/_copytextbutton.py
telegram/_dice.py
telegram/_forcereply.py
telegram/_forumtopic.py
telegram/_giveaway.py
telegram/_keyboardbutton.py
telegram/_keyboardbuttonpolltype.py
telegram/_keyboardbuttonrequest.py
telegram/_linkpreviewoptions.py
telegram/_loginurl.py
telegram/_menubutton.py
telegram/_message.py
telegram/_messageautodeletetimerchanged.py
telegram/_messageentity.py
telegram/_messageid.py
telegram/_messageorigin.py
telegram/_messagereactionupdated.py
telegram/_paidmedia.py
telegram/_poll.py
telegram/_proximityalerttriggered.py
telegram/_reaction.py
telegram/_reply.py
telegram/_replykeyboardmarkup.py
telegram/_replykeyboardremove.py
telegram/_sentwebappmessage.py
telegram/_shared.py
telegram/_story.py
telegram/_switchinlinequerychosenchat.py
telegram/_telegramobject.py
telegram/_update.py
telegram/_user.py
telegram/_userprofilephotos.py
telegram/_version.py
telegram/_videochat.py
telegram/_webappdata.py
telegram/_webappinfo.py
telegram/_webhookinfo.py
telegram/_writeaccessallowed.py
telegram/constants.py
telegram/error.py
telegram/helpers.py
telegram/py.typed
telegram/warnings.py
telegram/_files/__init__.py
telegram/_files/_basemedium.py
telegram/_files/_basethumbedmedium.py
telegram/_files/animation.py
telegram/_files/audio.py
telegram/_files/chatphoto.py
telegram/_files/contact.py
telegram/_files/document.py
telegram/_files/file.py
telegram/_files/inputfile.py
telegram/_files/inputmedia.py
antares_ptb-21.7.dist-info/METADATA
antares_ptb-21.7.dist-info/WHEEL
antares_ptb-21.7.dist-info/licenses/LICENSE
antares_ptb-21.7.dist-info/licenses/LICENSE.dual
antares_ptb-21.7.dist-info/licenses/LICENSE.lesser
antares_ptb-21.7.dist-info/RECORD
